pysdtest/Resampling_Functions.py
pysdtest/Test_Stat_Functions.py
pysdtest/__init__.py
pysdtest/pysdtest.py
pysdtest-0.0.21.dist-info/METADATA
pysdtest-0.0.21.dist-info/WHEEL
pysdtest-0.0.21.dist-info/top_level.txt
pysdtest-0.0.21.dist-info/RECORD
