Metadata-Version: 2.4
Name: PySDTest
Version: 0.0.21
Summary: A Python Package for Stochastic Dominance Tests
Home-page: https://github.com/lee-kyungho/pysdtest
Author: Kyungho Lee
Author-email: liikh1994@gmail.com
Project-URL: Bug Tracker, https://github.com/lee-kyungho/pysdtest/issues
Classifier: Programming Language :: Python :: 3
Classifier: License :: OSI Approved :: GNU General Public License v3 (GPLv3)
Classifier: Operating System :: OS Independent
Requires-Python: >=3.6
Requires-Dist: numpy
